ftvstt/__init__.py
ftvstt/exceptions.py
ftvstt/transcribers.py
ftvstt/transcripts.py
ftvstt/providers/__init__.py
ftvstt/providers/amazon.py
ftvstt/providers/bertin.py
ftvstt/providers/google.py
ftvstt/providers/vocapia.py
ftvstt-2.0.0.dist-info/METADATA
ftvstt-2.0.0.dist-info/WHEEL
ftvstt-2.0.0.dist-info/top_level.txt
ftvstt-2.0.0.dist-info/RECORD
