Metadata-Version: 2.1
Name: ftvstt
Version: 2.0.0
Summary: Transcription APIs encapsulation
Home-page: UNKNOWN
Author: France Télévisions innovations et développement
Author-email: pierre-andre.long@francetv.fr
License: UNKNOWN
Platform: UNKNOWN
Classifier: Programming Language :: Python :: 3
Classifier: License :: OSI Approved :: MIT License
Classifier: Operating System :: OS Independent
Requires-Dist: boto3 (==1.10.4)
Requires-Dist: google-cloud-speech (==1.2.0)
Requires-Dist: requests (==2.22.0)
